{
  "type": "minecraft:entity",
  "pools": [
    {
      "bonus_rolls": 0.0,
      "entries": [
        {
          "type": "minecraft:item",
          "name": "minecraft:totem_of_undying"
        }
      ],
      "rolls": 1.0
    },
    {
      "rolls": 1.0,
      "entries": [
        {
          "type": "item",
          "name": "supplementaries:cage",
          "conditions": [
            {
              "condition": "minecraft:random_chance_with_looting",
              "chance": 0.1,
              "looting_multiplier": 0.05
            }
          ],
          "functions": [
            {
              "function": "minecraft:set_nbt",
              "tag": "{BlockEntityTag: {MobHolder: {Name: \"Allay\", EntityData: {OnGround: 0, id: \"minecraft:allay\", Pos: [0.5, 0.20009998807907103, 0.5]}, UUID: [I;337490524, -1465561816, -1379577540, -880518522], Scale: 1.0}}}"
            }
          ]
        }
      ]
    },
    {
      "bonus_rolls": 0.0,
      "conditions": [
        {
          "condition": "minecraft:killed_by_player"
        }
      ],
      "entries": [
        {
          "type": "minecraft:item",
          "functions": [
            {
              "add": false,
              "count": {
                "type": "minecraft:uniform",
                "max": 1.0,
                "min": 0.0
              },
              "function": "minecraft:set_count"
            },
            {
              "count": {
                "type": "minecraft:uniform",
                "max": 1.0,
                "min": 0.0
              },
              "function": "minecraft:looting_enchant"
            }
          ],
          "name": "minecraft:emerald"
        }
      ],
      "rolls": 1.0
    }
  ]
}